img_to_webp/__init__.py
img_to_webp/convert.py
img_scale_to_webp-1.0.0.dist-info/METADATA
img_scale_to_webp-1.0.0.dist-info/WHEEL
img_scale_to_webp-1.0.0.dist-info/entry_points.txt
img_scale_to_webp-1.0.0.dist-info/top_level.txt
img_scale_to_webp-1.0.0.dist-info/RECORD
