Metadata-Version: 2.4
Name: img-scale-to-webp
Version: 1.0.0
Summary: A tool to convert images to WebP with a target file size.
Home-page: https://github.com/erhantrk/img-to-webp
Author: Erhan Türker
Author-email: erhantrk0122@gmail.com
Classifier: Programming Language :: Python :: 3
Classifier: License :: OSI Approved :: MIT License
Classifier: Operating System :: OS Independent
Requires-Python: >=3.6
Requires-Dist: Pillow
